[
  {
    "url": "https://ogrenci.iuc.edu.tr/tr/content/mevzuat/yonetmelikler",
    "filename": "ogrenci.iuc.edu.tr_tr_content_mevzuat_yonetmelikler.html",
    "type": "html"
  },
  {
    "url": "https://ogrenci.iuc.edu.tr/tr/content/mevzuat/yonergeler",
    "filename": "ogrenci.iuc.edu.tr_tr_content_mevzuat_yonergeler.html",
    "type": "html"
  },
  {
    "url": "https://ogrenci.iuc.edu.tr/tr/content/mevzuat/esaslar-kararlar-kilavuzlar",
    "filename": "ogrenci.iuc.edu.tr_tr_content_mevzuat_esaslar-kararlar-kilavuzlar.html",
    "type": "html"
  },
  {
    "url": "https://ogrenci.iuc.edu.tr/tr/content/mevzuat/kanunlar",
    "filename": "ogrenci.iuc.edu.tr_tr_content_mevzuat_kanunlar.html",
    "type": "html"
  },
  {
    "url": "https://ogrenci.iuc.edu.tr/tr/content/akademik-takvim/onlisans~2Flisans-akademik-takvim",
    "filename": "ogrenci.iuc.edu.tr_tr_content_akademik-takvim_onlisans~2Flisans-akademik-takvim.html",
    "type": "html"
  },
  {
    "url": "https://ogrenci.iuc.edu.tr/tr/content/sss/",
    "filename": "ogrenci.iuc.edu.tr_tr_content_sss_.html",
    "type": "html"
  },
  {
    "url": "https://ogrenci.iuc.edu.tr/tr/duyurular/1/1",
    "filename": "ogrenci.iuc.edu.tr_tr_duyurular_1_1.html",
    "type": "html"
  },
  {
    "url": "https://ogrenci.iuc.edu.tr/tr/duyurular/1/2",
    "filename": "ogrenci.iuc.edu.tr_tr_duyurular_1_2.html",
    "type": "html"
  },
  {
    "url": "https://ogrenci.iuc.edu.tr/tr/duyurular/1/3",
    "filename": "ogrenci.iuc.edu.tr_tr_duyurular_1_3.html",
    "type": "html"
  },
  {
    "url": "https://ogrenci.iuc.edu.tr/tr/duyurular/1/4",
    "filename": "ogrenci.iuc.edu.tr_tr_duyurular_1_4.html",
    "type": "html"
  },
  {
    "url": "https://ogrenci.iuc.edu.tr/tr/duyurular/1/5",
    "filename": "ogrenci.iuc.edu.tr_tr_duyurular_1_5.html",
    "type": "html"
  },
  {
    "url": "https://iuc.edu.tr/tr/content/aday-ogrenci/universitemiz-hakkinda",
    "filename": "iuc.edu.tr_tr_content_aday-ogrenci_universitemiz-hakkinda.html",
    "type": "html"
  },
  {
    "url": "https://cdn.iuc.edu.tr/FileHandler2.ashx?f=--2024-2025-cift-anadal-aday-ogrenci_638539775286536791.pdf",
    "filename": "f=--2024-2025-cift-anadal-aday-ogrenci_638539775286536791.pdf",
    "type": "pdf"
  },
  {
    "url": "https://cdn.iuc.edu.tr/FileHandler2.ashx?f=-cap-yonerge-senatoda-kabul-edilen-02-nisanda.pdf",
    "filename": "f=-cap-yonerge-senatoda-kabul-edilen-02-nisanda.pdf",
    "type": "pdf"
  },
  {
    "url": "https://cdn.iuc.edu.tr/FileHandler2.ashx?f=2024-2025-yandal-programlari.pdf",
    "filename": "f=2024-2025-yandal-programlari.pdf",
    "type": "pdf"
  },
  {
    "url": "https://iuc.edu.tr/tr/content/iuc-kart/iuc-kart-nedir",
    "filename": "iuc.edu.tr_tr_content_iuc-kart_iuc-kart-nedir.html",
    "type": "html"
  },
  {
    "url": "https://cdn.iuc.edu.tr/FileHandler2.ashx?f=iuc-kart-uye-ol_638575838965124910.pdf",
    "filename": "f=iuc-kart-uye-ol_638575838965124910.pdf",
    "type": "pdf"
  },
  {
    "url": "https://cdn.iuc.edu.tr/FileHandler2.ashx?f=iuc-kart-ekleme.pdf",
    "filename": "f=iuc-kart-ekleme.pdf",
    "type": "pdf"
  },
  {
    "url": "https://cdn.iuc.edu.tr/FileHandler2.ashx?f=a-guide-on-loading-credit.pdf",
    "filename": "f=a-guide-on-loading-credit.pdf",
    "type": "pdf"
  },
  {
    "url": "https://iuc.edu.tr/tr/",
    "filename": "iuc.edu.tr_tr_.html",
    "type": "html"
  }
]